fastapi_authlib_keycloak/__init__.py
fastapi_authlib_keycloak/adapter.py
fastapi_authlib_keycloak/builder.py
fastapi_authlib_keycloak/client.py
fastapi_authlib_keycloak/config.py
fastapi_authlib_keycloak/dependencies.py
fastapi_authlib_keycloak/errors.py
fastapi_authlib_keycloak/metrics.py
fastapi_authlib_keycloak/middleware.py
fastapi_authlib_keycloak/models.py
fastapi_authlib_keycloak/py.typed
fastapi_authlib_keycloak/refresh.py
fastapi_authlib_keycloak/validator.py
fastapi_authlib_keycloak-0.3.6.dist-info/licenses/LICENSE
fastapi_authlib_keycloak-0.3.6.dist-info/METADATA
fastapi_authlib_keycloak-0.3.6.dist-info/WHEEL
fastapi_authlib_keycloak-0.3.6.dist-info/top_level.txt
fastapi_authlib_keycloak-0.3.6.dist-info/RECORD
