Metadata-Version: 2.4
Name: fastapi-authlib-keycloak
Version: 0.3.6
Summary: Robust Keycloak integration for FastAPI using JWT/Introspection validation, RBAC, metrics, diagnostics and more.
Author-email: Harsha Krishnareddy <c0mpiler@ins8s.dev>
License: MIT License
Project-URL: Homepage, http://github.com/c0mpiler/fastapi-authlib-keycloak/
Project-URL: Bug Tracker, http://github.com/c0mpiler/fastapi-authlib-keycloak/issues
Project-URL: Repository, http://github.com/c0mpiler/fastapi-authlib-keycloak/
Keywords: fastapi,keycloak,authentication,authorization,oauth2,oidc,jwt,security,middleware,rbac,sso,auth,authlib,keycloak-authlib,keycloak-authlib-fastapi,keycloak-fastapi,fastapi-keycloak,fastapi-keycloak-authlib,authlib-fastapi,authlib-fastapi-keycloak
Classifier: Development Status :: 4 - Beta
Classifier: Framework :: FastAPI
Classifier: Intended Audience :: Developers
Classifier: License :: OSI Approved :: MIT License
Classifier: Operating System :: OS Independent
Classifier: Programming Language :: Python :: 3
Classifier: Programming Language :: Python :: 3.8
Classifier: Programming Language :: Python :: 3.9
Classifier: Programming Language :: Python :: 3.10
Classifier: Programming Language :: Python :: 3.11
Classifier: Programming Language :: Python :: 3.12
Classifier: Topic :: Internet :: WWW/HTTP :: Session
Classifier: Topic :: Security
Classifier: Topic :: Software Development :: Libraries :: Python Modules
Classifier: Typing :: Typed
Requires-Python: >=3.8
License-File: LICENSE
Requires-Dist: fastapi>=0.95.0
Requires-Dist: httpx[http2]>=0.24.0
Requires-Dist: pydantic<3.0.0,>=1.10.0
Requires-Dist: PyJWT[crypto]>=2.6.0
Requires-Dist: cachetools>=5.0.0
Requires-Dist: certifi>=2023.7.22
Provides-Extra: test
Requires-Dist: pytest>=7.0.0; extra == "test"
Requires-Dist: pytest-asyncio>=0.20.0; extra == "test"
Requires-Dist: pytest-cov>=4.0.0; extra == "test"
Requires-Dist: respx>=0.20.0; extra == "test"
Requires-Dist: freezegun>=1.2.0; extra == "test"
Provides-Extra: dev
Requires-Dist: fastapi-authlib-keycloak[test]; extra == "dev"
Requires-Dist: ruff; extra == "dev"
Requires-Dist: mypy; extra == "dev"
Requires-Dist: pre-commit; extra == "dev"
Requires-Dist: build; extra == "dev"
Requires-Dist: twine; extra == "dev"
Dynamic: license-file
